cosevadb/__init__.py
cosevadb/cosevadb.py
cosevadb-0.0.3.dist-info/LICENSE
cosevadb-0.0.3.dist-info/METADATA
cosevadb-0.0.3.dist-info/WHEEL
cosevadb-0.0.3.dist-info/top_level.txt
cosevadb-0.0.3.dist-info/RECORD
