Metadata-Version: 2.1
Name: cosevadb
Version: 0.0.3
Summary: Light weight SQL database designed to manage data in csv format
Home-page: https://github.com/ppml38/cosevadb
Author: Prakash Maria Liju P
Author-email: ppml38@gmail.com
License: UNKNOWN
Platform: UNKNOWN
Classifier: Programming Language :: Python :: 3
Classifier: License :: OSI Approved :: MIT License
Classifier: Operating System :: OS Independent
Requires-Python: >=3.6
